{
  "id": 501,
  "name": "Fury Crocodile",
  "location": "Mayan Forest",
  "image": "data/Monster_Images/monster-501.png",
  "element": "Fire",
  "drops": [
    {
      "name": "Dinosaur Tooth",
      "itemId": 7809,
      "itemFile": "material-7809.json",
      "itemCategory": "material"
    },
    {
      "name": "Cod",
      "itemId": 7488,
      "itemFile": "material-7488.json",
      "itemCategory": "material"
    },
    {
      "name": "Claw",
      "itemId": 7775,
      "itemFile": "material-7775.json",
      "itemCategory": "material"
    }
  ],
  "stats": {
    "level": 78,
    "hp": 860,
    "sp": 710,
    "catchable": "Yes",
    "spd": 211,
    "str": 47,
    "con": 52,
    "int": 43,
    "wis": 45,
    "agi": 47
  }
}